pyhtmx/__init__.py
pyhtmx/html_tag.py
pyhtmx/html_tag_list.py
pyhtmx_lib-0.1.0.dist-info/LICENSE
pyhtmx_lib-0.1.0.dist-info/METADATA
pyhtmx_lib-0.1.0.dist-info/WHEEL
pyhtmx_lib-0.1.0.dist-info/top_level.txt
pyhtmx_lib-0.1.0.dist-info/RECORD
