Metadata-Version: 2.2
Name: pyhtmx-lib
Version: 0.1.0
Summary: A simple wrapper/generator for HTMX pages
Author-email: Flávio De Melo <flavio.eler@gmail.com>
Project-URL: Homepage, https://github.com/femelo/pyhtmx
Project-URL: Issues, https://github.com/femelo/pyhtmx/issues
Classifier: Programming Language :: Python :: 3
Classifier: License :: OSI Approved :: MIT License
Classifier: Operating System :: OS Independent
Requires-Python: >=3.9
License-File: LICENSE
